{"internalDate": "1481982718000", "historyId": "5788575", "payload": {"mimeType": "text/plain", "headers": [{"name": "Return-Path", "value": "<nhu2000@gmail.com>"}, {"name": "Received", "value": "from [192.168.51.169] (50-193-217-220-static.hfc.comcastbusiness.net. [50.193.217.220])        by smtp.gmail.com with ESMTPSA id 65sm19323802pfl.21.2016.12.17.05.51.59        for <nhu2000@gmail.com>        (version=TLS1 cipher=ECDHE-RSA-AES128-SHA bits=128/128);        Sat, 17 Dec 2016 05:52:00 -0800 (PST)"}, {"name": "Content-Type", "value": "text/plain; charset=us-ascii"}, {"name": "Content-Transfer-Encoding", "value": "7bit"}, {"name": "From", "value": "Nanfang Hu <nhu2000@gmail.com>"}, {"name": "Mime-Version", "value": "1.0 (1.0)"}, {"name": "Date", "value": "Sat, 17 Dec 2016 05:51:58 -0800"}, {"name": "Subject", "value": "道教名山仙遊趣～徽州齊雲山"}, {"name": "Message-Id", "value": "<29AA2410-DC9A-4535-BC7A-6AF7D507B9F3@gmail.com>"}, {"name": "To", "value": "nhu2000@gmail.com"}, {"name": "X-Mailer", "value": "iPhone Mail (14A403)"}], "body": {"data": "aHR0cHM6Ly95b3V0dS5iZS9NdDlVNDFZV2RmNA0KDQoNClNlbnQgZnJvbSBteSBpUGhvbmUNCg==", "size": 55}, "partId": "", "filename": ""}, "snippet": "https://youtu.be/Mt9U41YWdf4 Sent from my iPhone", "sizeEstimate": 773, "threadId": "1590d0db9be71cb6", "labelIds": ["IMPORTANT", "Label_47", "SENT"], "id": "1590d0db9be71cb6"}